clipt/__init__.py
clipt/cl_plot.py
clipt/plot.py
clipt-1.0.15.dist-info/LICENSE
clipt-1.0.15.dist-info/METADATA
clipt-1.0.15.dist-info/WHEEL
clipt-1.0.15.dist-info/entry_points.txt
clipt-1.0.15.dist-info/top_level.txt
clipt-1.0.15.dist-info/zip-safe
clipt-1.0.15.dist-info/RECORD
