Metadata-Version: 2.1
Name: clipt
Version: 1.0.15
Summary: clipt makes graphs using matplotlib from the command line
Home-page: https://bitbucket.org/stephenwasilewski/clipt
Author: Stephen Wasilewski
Author-email: stephen@coolshadow.com
License: Mozilla Public License 2.0 (MPL 2.0)
Project-URL: documentation, https://clipt.readthedocs.io/
Keywords: clipt
Classifier: Development Status :: 2 - Pre-Alpha
Classifier: License :: OSI Approved :: Mozilla Public License 2.0 (MPL 2.0)
Classifier: Natural Language :: English
Classifier: Programming Language :: Python :: 3.6
Classifier: Programming Language :: Python :: 3.7
Requires-Python: >=3.6
License-File: LICENSE
Requires-Dist: numpy
Requires-Dist: matplotlib
Requires-Dist: clasp
Requires-Dist: scipy
